MANIFEST.in
readme.md
setup.py
emerald/__init__.py
emerald/config.py
emerald/database.py
emerald/service.py
emerald.egg-info/PKG-INFO
emerald.egg-info/SOURCES.txt
emerald.egg-info/dependency_links.txt
emerald.egg-info/entry_points.txt
emerald.egg-info/not-zip-safe
emerald.egg-info/requires.txt
emerald.egg-info/top_level.txt
emerald/static/__init__.py
emerald/static/css/materialize.min.css
emerald/static/fonts/roboto/Roboto-Bold.eot
emerald/static/fonts/roboto/Roboto-Bold.ttf
emerald/static/fonts/roboto/Roboto-Bold.woff
emerald/static/fonts/roboto/Roboto-Bold.woff2
emerald/static/fonts/roboto/Roboto-Light.eot
emerald/static/fonts/roboto/Roboto-Light.ttf
emerald/static/fonts/roboto/Roboto-Light.woff
emerald/static/fonts/roboto/Roboto-Light.woff2
emerald/static/fonts/roboto/Roboto-Medium.eot
emerald/static/fonts/roboto/Roboto-Medium.ttf
emerald/static/fonts/roboto/Roboto-Medium.woff
emerald/static/fonts/roboto/Roboto-Medium.woff2
emerald/static/fonts/roboto/Roboto-Regular.eot
emerald/static/fonts/roboto/Roboto-Regular.ttf
emerald/static/fonts/roboto/Roboto-Regular.woff
emerald/static/fonts/roboto/Roboto-Regular.woff2
emerald/static/fonts/roboto/Roboto-Thin.eot
emerald/static/fonts/roboto/Roboto-Thin.ttf
emerald/static/fonts/roboto/Roboto-Thin.woff
emerald/static/fonts/roboto/Roboto-Thin.woff2
emerald/static/js/jquery-2.1.1.min.js
emerald/static/js/materialize.min.js
emerald/templates/__init__.py
emerald/templates/home.html
emerald/templates/services.html
emerald/templates/status.html
emerald/templates/template.html
emerald/tests/__init__.py