Metadata-Version: 1.0
Name: emerald
Version: 0.0.1.dev0
Summary: Service registry using pymicroservice
Home-page: https://github.com/vladcalin/emerald
Author: Vlad Calin
Author-email: vlad.s.calin@gmail.com
License: MIT
Keywords: microservice,cloud,rpc,compute,service,service,regiistry
Platform: UNKNOWN
